fstring/__init__.py
simple_fstring-0.1.dist-info/LICENSE
simple_fstring-0.1.dist-info/METADATA
simple_fstring-0.1.dist-info/WHEEL
simple_fstring-0.1.dist-info/top_level.txt
simple_fstring-0.1.dist-info/RECORD
