Metadata-Version: 2.1
Name: simple-fstring
Version: 0.1
Summary: a simple basic f-string like behavior in Python 2
Home-page: https://github.com/hefvcjm/simple-fstring
Author: hef
Author-email: 
License: UNKNOWN
Platform: UNKNOWN
